tp2conceptionlogicielle/__init__.py
tp2conceptionlogicielle/__main__.py
tp2conceptionlogicielle/ratio.py
tp2conceptionlogicielle-0.1.0.dist-info/LICENSE
tp2conceptionlogicielle-0.1.0.dist-info/METADATA
tp2conceptionlogicielle-0.1.0.dist-info/WHEEL
tp2conceptionlogicielle-0.1.0.dist-info/RECORD
