Metadata-Version: 2.1
Name: tp2conceptionlogicielle
Version: 0.1.0
Summary: 
License: MIT
Author: ragatzino
Author-email: antoine.brunetti@insee.fr
Requires-Python: >=3.10,<4.0
Classifier: License :: OSI Approved :: MIT License
Classifier: Programming Language :: Python :: 3
Classifier: Programming Language :: Python :: 3.10
Classifier: Programming Language :: Python :: 3.11
Requires-Dist: fuzzywuzzy (==0.18.0)
Requires-Dist: python-Levenshtein (==0.20.9)
Requires-Dist: python-dotenv (==0.21.0)
